README.md
mdbom/__init__.py
mdbom/bom/__init__.py
mdbom/bom/bom.py
mdbom/bom/processor.py
mdbom/bom/urls.py
mdbom/md/__init__.py
mdbom/md/md.py
mdbom/mdbom.py
pyproject.toml
mdbom-0.3.0.dist-info/entry_points.txt
mdbom-0.3.0.dist-info/LICENSE
mdbom-0.3.0.dist-info/WHEEL
mdbom-0.3.0.dist-info/METADATA
mdbom-0.3.0.dist-info/RECORD
