Metadata-Version: 2.1
Name: mdbom
Version: 0.3.0
Summary: Transform SBOM to Markdown
Home-page: https://haro87.github.io/mdbom/
License: MIT
Author: Robert Hansel
Author-email: code@fam-hansel.de
Requires-Python: >=3.7,<4.0
Classifier: License :: OSI Approved :: MIT License
Classifier: Programming Language :: Python :: 3
Classifier: Programming Language :: Python :: 3.10
Classifier: Programming Language :: Python :: 3.7
Classifier: Programming Language :: Python :: 3.8
Classifier: Programming Language :: Python :: 3.9
Requires-Dist: Jinja2 (>=2.11.3,<3.0.0)
Requires-Dist: MarkupSafe (==2.0.1)
Requires-Dist: click (>=8.1.0,<9.0.0)
Project-URL: Repository, https://github.com/HaRo87/mdbom
